nonebot_plugin_liarsbar/__init__.py
nonebot_plugin_liarsbar/config.py
nonebot_plugin_liarsbar/liars/__init__.py
nonebot_plugin_liarsbar/liars/definitions.py
nonebot_plugin_liarsbar/liars/main.py
nonebot_plugin_liarsbar-1.0.5.dist-info/LICENSE
nonebot_plugin_liarsbar-1.0.5.dist-info/METADATA
nonebot_plugin_liarsbar-1.0.5.dist-info/WHEEL
nonebot_plugin_liarsbar-1.0.5.dist-info/top_level.txt
nonebot_plugin_liarsbar-1.0.5.dist-info/RECORD
