Metadata-Version: 2.2
Name: nonebot-plugin-liarsbar
Version: 1.0.5
Summary: 用于 Nonebot2 的 liar's bar 插件
Author-email: SnowFox4004 <snow_fox08@163.com>
License: AGPL
Project-URL: homepage, https://github.com/SnowFox4004/nonebot-plugin-liarsbar
Project-URL: repository, https://github.com/SnowFox4004/nonebot-plugin-liarsbar
Project-URL: bug-tracker, https://github.com/SnowFox4004/nonebot-plugin-liarsbar
Requires-Python: >=3.10
License-File: LICENSE
Requires-Dist: nonebot2>=2.3.3
Requires-Dist: nonebot-plugin-alconna>=0.52.1
Requires-Dist: nonebot-plugin-uninfo>=0.4.0
Requires-Dist: anyio>=4.6.0
